drf_sse/__init__.py
drf_sse/mixins.py
drf_sse/renderers.py
drf_sse/renders.py
drf_sse/responses.py
drf_sse/version.json
drf_sse-1.0.1.dist-info/METADATA
drf_sse-1.0.1.dist-info/WHEEL
drf_sse-1.0.1.dist-info/top_level.txt
drf_sse-1.0.1.dist-info/RECORD
