Metadata-Version: 2.1
Name: drf-sse
Version: 1.0.1
Summary: SSE(Server-Sent Events) for DjangoRestFramework
Home-page: https://github.com/suqingdong/drf_sse
Author: suqingdong
Author-email: suqingdong1114@gmail.com
License: MIT License
Platform: UNKNOWN
Classifier: Development Status :: 5 - Production/Stable
Classifier: Operating System :: OS Independent
Classifier: Intended Audience :: Developers
Classifier: License :: OSI Approved :: MIT License
Classifier: Programming Language :: Python
Classifier: Programming Language :: Python :: 3
Classifier: Programming Language :: Python :: 3.8
Classifier: Programming Language :: Python :: 3.9
Classifier: Programming Language :: Python :: 3.10
Classifier: Programming Language :: Python :: 3.11
Classifier: Topic :: Software Development :: Libraries
Requires-Python: >=3.8
Requires-Dist: djangorestframework
